{
	"kind" : "toolchains",
	"toolchains" : 
	[
		{
			"compiler" : 
			{
				"id" : "Clang",
				"implicit" : 
				{
					"includeDirectories" : 
					[
						"C:/dev/llvm-mingw/lib/clang/22/include",
						"C:/dev/llvm-mingw/include"
					],
					"linkDirectories" : 
					[
						"C:/dev/llvm-mingw/x86_64-w64-mingw32/lib",
						"C:/dev/llvm-mingw/x86_64-w64-mingw32/mingw/lib",
						"C:/dev/llvm-mingw/lib",
						"C:/dev/llvm-mingw/lib/clang/22/lib/windows"
					],
					"linkFrameworkDirectories" : [],
					"linkLibraries" : 
					[
						"mingw32",
						"unwind",
						"moldname",
						"mingwex",
						"advapi32",
						"shell32",
						"user32",
						"kernel32",
						"mingw32",
						"unwind",
						"moldname",
						"mingwex",
						"kernel32"
					]
				},
				"path" : "C:/dev/llvm-mingw/bin/clang.exe",
				"version" : "22.1.0"
			},
			"language" : "C",
			"sourceFileExtensions" : 
			[
				"c",
				"m"
			]
		},
		{
			"compiler" : 
			{
				"implicit" : {},
				"path" : "C:/dev/llvm-mingw/bin/windres.exe"
			},
			"language" : "RC",
			"sourceFileExtensions" : 
			[
				"rc",
				"RC"
			]
		}
	],
	"version" : 
	{
		"major" : 1,
		"minor" : 0
	}
}
